<?xml version="1.0" encoding="utf-8"?>
<!DOCTYPE hibernate-mapping PUBLIC "-//Hibernate/Hibernate Mapping DTD 3.0//EN"
"http://www.hibernate.org/dtd/hibernate-mapping-3.0.dtd">
<!-- 
    Mapping file autogenerated by MyEclipse Persistence Tools
-->
<hibernate-mapping>
    <class name="com.ruiyi.wechat.po.ServiceParameter" table="service_parameter" catalog="cloud">
        <id name="id" type="java.lang.Integer">
            <column name="ID" />
            <generator class="identity" />
        </id>
        <many-to-one name="parameter" class="com.ruiyi.wechat.po.Parameter" fetch="select">
            <column name="PARAMETER_ID" not-null="true" />
        </many-to-one>
        <property name="serviceId" type="java.lang.Integer">
            <column name="SERVICE_ID" />
        </property>
        <property name="state" type="java.lang.Boolean">
            <column name="STATE" />
        </property>
        <property name="starttime" type="java.util.Date">
            <column name="STARTTIME" length="10" />
        </property>
        <property name="endtime" type="java.util.Date">
            <column name="ENDTIME" length="10" />
        </property>
    </class>
</hibernate-mapping>
